writing_style_converter/__init__.py
writing_style_converter/enums.py
writing_style_converter/factory_style.py
writing_style_converter/preparation_style.py
writing_style_converter/wsc.py
writing_style_converter-0.0.12.dist-info/LICENSE
writing_style_converter-0.0.12.dist-info/METADATA
writing_style_converter-0.0.12.dist-info/WHEEL
writing_style_converter-0.0.12.dist-info/top_level.txt
writing_style_converter-0.0.12.dist-info/RECORD
