Metadata-Version: 2.1
Name: writing-style-converter
Version: 0.0.12
Summary: A library for converting naming styles in Python code. telegram: "@Orlov_SA"
Author-email: Stepan Orlov <stepan.nadym@gmail.com>
Project-URL: Homepage, https://github.com/OrlovSA/writing_style_converter
Classifier: Programming Language :: Python :: 3
Classifier: License :: OSI Approved :: MIT License
Requires-Python: >=3.8
License-File: LICENSE
